WasatchUSB-1.0.1.dist-info/RECORD
WasatchUSB-1.0.1.dist-info/METADATA
WasatchUSB-1.0.1.dist-info/DESCRIPTION.rst
WasatchUSB-1.0.1.dist-info/WHEEL
WasatchUSB-1.0.1.dist-info/top_level.txt
WasatchUSB-1.0.1.dist-info/metadata.json
wasatchusb/utils.py
wasatchusb/__init__.py
wasatchusb/camera.py
