Metadata-Version: 2.0
Name: WasatchUSB
Version: 1.0.1
Summary: USB cameras and devices from Wasatch Photonics
Home-page: https://github.com/nharringtonwasatch/WasatchUSB
Author: Nathan Harrington
Author-email: nharrington@wasatchphotonics.com
License: UNKNOWN
Download-URL: https://github.com/nharringtonwasatch/WasatchUSB
Platform: UNKNOWN
Requires-Dist: phidgeter
Requires-Dist: pyusb
Requires-Dist: numpy
